{"The devil fetch ye, ye ragamuffin rapscallions; ye are all asleep. Stop snoring, ye sleepers": "\ud83d\ude08\ud83d\udd25\ud83d\udce5\ud83d\udc49, \ud83d\udc49\ud83d\udc55\ud83d\udd04\ud83d\udc82\u200d\u2642\ufe0f\ud83d\udc82\u200d\u2640\ufe0f; \ud83d\udc49\ud83d\udc65\ud83d\ude34\ud83d\udca4\ud83d\udca4. \u26d4\ufe0f\ud83d\udca4\ud83d\udca4, \ud83d\udc49\ud83d\ude34\ud83d\udca4\ud83d\udca4\ud83d\udc65", "sharks now freshly and more keenly allured by the before pent blood which began to flow from the carcass": "\ud83e\udd88\ud83e\udd88\ud83e\udd88\ud83d\udd1c\ud83c\udf3f\ud83c\udd95\u2795\ud83d\udd2a\ud83c\udfaf\ud83d\udc89\ud83d\udca7\ud83d\udfe5\ud83e\udd24\ud83c\udfac\ud83d\udcab\u27a1\ufe0f\ud83e\udd69\ud83c\udf56\ud83d\udd2e\ud83d\udc94\ud83d\udc9f\ud83d\udd50\ud83c\udf0a", "BLOODY BATTLE IN AFFGHANISTAN.": "\ud83d\udc89\u2694\ufe0f\ud83e\udd3c\u200d\u2642\ufe0f\ud83d\udd25\ud83c\udde6\ud83c\uddeb", "So in this vale of Death, God girds us round; and over all our gloom, the sun of Righteousness still shines a beacon and a hope.": "\ud83d\ude0c\u27a1\ufe0f\ud83d\udc80\u26f0\ufe0f, \ud83d\ude4f\ud83d\udcaa\ud83c\udf0d\u21aa\ufe0f; \u2b06\ufe0f\ud83d\ude1e\ud83c\udf11, \u2600\ufe0f\u2696\ufe0f\ud83d\udca1\u2728\ud83d\udea6\ud83d\udca1\ud83d\udd6f\ufe0f\ud83d\udca1\ud83e\udd1e.", "Consider, once more, the universal cannibalism of the sea": "\ud83e\udd14,\ud83d\udd02, \ud83c\udf10\ud83c\udf74\ud83c\udf0a", "Look at the crowds of water-gazers there.": "\ud83d\udc40\ud83d\udc65\ud83d\udc65\ud83d\udc65\u26f2\ud83d\udc40\ud83d\udc65\ud83d\udc65\ud83d\udc65", "What all men\u2019s minds and opinions but Loose-Fish?": "\u2753\ud83e\udd14\ud83d\udc68\u200d\ud83d\udc69\u200d\ud83d\udc67\u200d\ud83d\udc66\ud83d\udcad\ud83d\udcac\ud83d\udc1f\ud83d\udca8", "He announced himself as the archangel Gabriel, and commanded the captain to jump overboard.": "\ud83d\udde3\ufe0f\ud83d\udc64\ud83d\udd1c\ud83d\udc7cGabriel, \ud83c\udfa4\u26f4\ufe0f\ud83d\udc68\u200d\u2708\ufe0f\ud83d\udc49\u23e9\ud83c\udf0a", "Quick! forge me the harpoon.": "\u26a1\ufe0f\ud83d\udd28\ud83d\udd25\ud83d\udee0\ufe0f\ud83d\udc33\ud83d\udd31", "all of us are Ahabs": "\ud83c\udf0d\ud83d\udc6b\ud83d\udc6c\ud83d\udc6d\u27a1\ufe0f\ud83d\udc0b\ud83c\udfa3\ud83e\uddd4\ud83c\udffd", "as if, the longer linked with life, the less man has to do with aught that looks like death": "\ud83e\udd14\ud83d\udcad, \u23f3\ud83d\udd17\ud83e\uddd1\u200d\ud83e\udd1d\u200d\ud83e\uddd1\ud83c\udf31\ud83c\udf0d, \u2796\ud83d\udd7a\ud83d\udd0e\ud83e\udd37\u200d\u2642\ufe0f\ud83d\udd1c\ud83d\udc80\ud83d\udc40", "Beelzebub himself might climb up the side and step down into the cabin to chat with the captain, and it would not create any unsubduable excitement in the forecastle.": "\ud83d\ude08\ud83d\udc63\u2b06\ufe0f\ud83d\udc48\ud83c\udfd4\ufe0f\u2795\ud83d\udc83\u2b07\ufe0f\ud83d\udeaa\ud83d\udea2\ud83d\udde3\ufe0f\ud83d\udde3\ufe0f\ud83d\udc6e\u200d\u2642\ufe0f, \u2795\ud83d\udeab\ud83c\udf2a\ufe0f\ud83e\udd2f\ud83d\udd25\u2728\ud83c\udfaa\ud83c\udf89\ud83d\udd26.", "a score of voices from all parts of the vessel, simultaneously with the three notes from aloft, shouted forth the accustomed cry": "\ud83d\udd22\ud83d\udde3\ufe0f\ud83d\udde3\ufe0f\ud83d\udde3\ufe0f\ud83d\udd00\ud83c\udf10\ud83d\udee5\ufe0f, \u23f1\ufe0f\ud83d\udc65\ud83d\udc65\ud83d\udc65\ud83c\udfb5\ud83c\udfb5\ud83c\udfb5\ud83d\udd1d, \ud83d\udd0a\ud83d\udd0a\ud83d\udd0a\ud83d\udce3\ud83d\udce3\ud83d\udce3\ud83d\udde3\ufe0f\ud83d\udce2\ud83d\udce2\ud83d\udce2\ud83d\udd00\ud83d\udd27\ud83d\udc65\ud83d\udc65\ud83d\udc65\ud83d\udde3\ufe0f\ud83d\udde3\ufe0f\ud83d\udde3\ufe0f", "this earthly air, whether ashore or afloat, is terribly infected with the nameless miseries of the numberless mortals who have died exhaling it": "\ud83c\udf0d\ud83d\udca8, \ud83c\udfde\ufe0f\ud83d\udea2, \ud83d\ude31\ud83d\ude37 \ud83d\udeab\ud83d\udcdb \ud83d\ude22\ud83d\ude22 \ud83c\udf10\ud83d\udc80 \ud83d\udc65 \ud83d\udc94\ud83d\ude35 \ud83d\udcac\ud83c\udf2c\ufe0f\ud83d\udc4b", "the first boat always hovers at hand to assist its consort": "1\ufe0f\u20e3\ud83d\udea4\ud83d\udd04\u270b\ud83c\udd98\ud83e\udd1d\ud83d\udea4", "Be cool at the equator; keep thy blood fluid at the Pole.": "\ud83d\ude0e\ud83c\udd92\ud83c\udf0d\ud83c\udf13;\ud83e\udd32\ud83e\ude78\ud83d\udca7\ud83d\udccd\ud83c\udfd4\ufe0f.", "But when Leviathan is the text, the case is altered.": "\ud83d\udd0d\ud83d\udc09\ud83d\udcdc, \ud83d\udcbc\ud83d\udd04", "For the most part, in this tropic whaling life, a sublime uneventfulness invests you": "\ud83d\udc49\ud83c\udffb\ud83c\udf0f\u2696\ufe0f, \ud83c\udf34\ud83d\udc33\ud83c\udfa3\ud83c\udfde\ufe0f, \ud83d\ude4c\ud83c\udf0c\ud83d\udcc5\ud83e\udde5\ud83d\udc64"}